{
  "prove_consecutive_2_Inbox": "77128",
  "prove_consecutive_2_InboxOptimized1": "69510",
  "prove_consecutive_2_InboxOptimized2": "66045",
  "prove_consecutive_3_Inbox": "112376",
  "prove_consecutive_3_InboxOptimized1": "75103",
  "prove_consecutive_3_InboxOptimized2": "71699",
  "prove_consecutive_5_Inbox": "183132",
  "prove_consecutive_5_InboxOptimized1": "86493",
  "prove_consecutive_5_InboxOptimized2": "82566",
  "prove_gaps_1_Inbox": "77193",
  "prove_gaps_1_InboxOptimized1": "121268",
  "prove_gaps_1_InboxOptimized2": "115979",
  "prove_gaps_2_Inbox": "112550",
  "prove_gaps_2_InboxOptimized1": "178677",
  "prove_gaps_2_InboxOptimized2": "171598",
  "prove_mixed_groups_Inbox": "183311",
  "prove_mixed_groups_InboxOptimized1": "138382",
  "prove_mixed_groups_InboxOptimized2": "132580",
  "prove_reverse_Inbox": "112399",
  "prove_reverse_InboxOptimized1": "178537",
  "prove_reverse_InboxOptimized2": "171529",
  "prove_single_Inbox": "43963",
  "prove_single_InboxOptimized1": "65843",
  "prove_single_InboxOptimized2": "62637"
}