{
  "prove_consecutive_2_Inbox": "77703",
  "prove_consecutive_2_InboxOptimized1": "70090",
  "prove_consecutive_2_InboxOptimized2": "66549",
  "prove_consecutive_3_Inbox": "113195",
  "prove_consecutive_3_InboxOptimized1": "75690",
  "prove_consecutive_3_InboxOptimized2": "72207",
  "prove_consecutive_5_Inbox": "184449",
  "prove_consecutive_5_InboxOptimized1": "87096",
  "prove_consecutive_5_InboxOptimized2": "83086",
  "prove_gaps_1_Inbox": "77772",
  "prove_gaps_1_InboxOptimized1": "121957",
  "prove_gaps_1_InboxOptimized2": "116522",
  "prove_gaps_2_Inbox": "113376",
  "prove_gaps_2_InboxOptimized1": "179668",
  "prove_gaps_2_InboxOptimized2": "172372",
  "prove_mixed_groups_Inbox": "184634",
  "prove_mixed_groups_InboxOptimized1": "139470",
  "prove_mixed_groups_InboxOptimized2": "133514",
  "prove_reverse_Inbox": "113220",
  "prove_reverse_InboxOptimized1": "179523",
  "prove_reverse_InboxOptimized2": "172300",
  "prove_single_Inbox": "44373",
  "prove_single_InboxOptimized1": "66225",
  "prove_single_InboxOptimized2": "62945"
}
