{
  "index": {
    "display": "hidden",
    "title": "Taiko",
    "type": "page",
    "theme": {
      "layout": "raw"
    }
  },
  "docs": {
    "title": "Docs",
    "type": "page"
  },
  "showcase": {
    "title": "Showcase",
    "type": "page",
    "theme": {
      "typesetting": "article",
      "layout": "full"
    }
  },
  "blog": {
    "title": "Blog ↗",
    "type": "page",
    "href": "https://mirror.xyz/labs.taiko.eth",
    "newWindow": true
  },
  "bridge": {
    "title": "Bridge ↗",
    "type": "page",
    "href": "https://bridge.a2.taiko.xyz",
    "newWindow": true
  },
  "uniswap": {
    "title": "Swap ↗",
    "type": "page",
    "href": "https://swap.a2.taiko.xyz",
    "newWindow": true
  },
  "status": {
    "title": "Status ↗",
    "type": "page",
    "href": "https://status.a2.taiko.xyz",
    "newWindow": true
  },
  "explorers": {
    "title": "Explorers",
    "type": "menu",
    "items": {
      "l1-block-explorer": {
        "title": "Sepolia (Etherscan) ↗",
        "href": "https://sepolia.etherscan.io",
        "newWindow": true
      },
      "l2-block-explorer": {
        "title": "Taiko (Blockscout) ↗",
        "href": "https://explorer.a2.taiko.xyz",
        "newWindow": true
      }
    }
  },
  "feedback": {
    "title": "Feedback ↗",
    "type": "page",
    "href": "https://forms.gle/RZsweAPy5RhQSP6j7",
    "newWindow": true
  }
}
